latex_document_reader/__init__.py
latex_document_reader/latex_document_reader.py
latex_document_reader-1.0.1.dist-info/LICENSE
latex_document_reader-1.0.1.dist-info/METADATA
latex_document_reader-1.0.1.dist-info/WHEEL
latex_document_reader-1.0.1.dist-info/top_level.txt
latex_document_reader-1.0.1.dist-info/RECORD
