Metadata-Version: 2.1
Name: latex-document-reader
Version: 1.0.1
Summary: A Python library for reading LaTeX documents and processing BibTeX files
Home-page: https://github.com/ozanil/LaTeXDocumentReader.git
Author: Anıl ÖZ
Author-email: anil.oz@icloud.com
Keywords: latex document reader bibtex
Classifier: Development Status :: 4 - Beta
Classifier: Intended Audience :: Developers
Classifier: License :: OSI Approved :: MIT License
Classifier: Programming Language :: Python :: 3
Classifier: Programming Language :: Python :: 3.6
Classifier: Programming Language :: Python :: 3.7
Classifier: Programming Language :: Python :: 3.8
Classifier: Programming Language :: Python :: 3.9
Requires-Python: >=3.6
License-File: LICENSE
